{"experiment_id": "cd52e0ed-8d0d-4002-b0d3-0b64459c2de8", "algorithm_name": "XGBClassifier", "module_name": "xgboost", "hyperparameter_key": "XyJiCWyRcloZip7NOC9CJXrRxzZgbMRjdYeQ_96gtAg=", "cross_experiment_key": "RAg0E1AlMwbRNAvJ0Kp1HfRfnziUnH1-BS-v2mTijQk=", "final_evaluations": {"in_fold": null, "oof": {"roc_auc_score": 0.9464153585962687}, "holdout": null}, "hyperparameters": {"model_initializer": "wxU5h7cHVipr2adj8yCDCGfLavr6G3OllAFEMz9F0XQ=", "model_init_params": {"max_depth": 3, "learning_rate": 0.1, "n_estimators": 100, "verbosity": 1, "silent": null, "objective": "reg:linear", "booster": "gbtree", "n_jobs": 1, "nthread": null, "gamma": 0, "min_child_weight": 1, "max_delta_step": 0, "subsample": 1, "colsample_bytree": 1, "colsample_bylevel": 1, "colsample_bynode": 1, "reg_alpha": 0, "reg_lambda": 1, "scale_pos_weight": 1, "base_score": 0.5, "missing": null}, "model_extra_params": {}, "feature_engineer": {"steps": [], "do_validate": false, "datasets": {}}, "feature_selector": ["mean_radius", "mean_texture", "mean_perimeter", "mean_area", "mean_smoothness", "mean_compactness", "mean_concavity", "mean_concave_points", "mean_symmetry", "mean_fractal_dimension", "radius_error", "texture_error", "perimeter_error", "area_error", "smoothness_error", "compactness_error", "concavity_error", "concave_points_error", "symmetry_error", "fractal_dimension_error", "worst_radius", "worst_texture", "worst_perimeter", "worst_area", "worst_smoothness", "worst_compactness", "worst_concavity", "worst_concave_points", "worst_symmetry", "worst_fractal_dimension"]}, "cross_experiment_parameters": {"metrics_params": {"metrics": {"roc_auc_score": {"name": "roc_auc_score", "metric_function": "28EZWaPC6Db3ujgdGSJpjE2cssdPPNXiBBTouW3zlj4=", "direction": "max"}}}, "cv_params": {"n_splits": 10, "shuffle": true, "random_state": 32}, "target_column": ["target"], "id_column": null, "do_predict_proba": false, "prediction_formatter": "VEasLH6aWTroBbAmwb49PBwPBPGT0xsIXexVGSOdTt8=", "train_dataset": "6F-A0LbNFIKdWM22eWlHyksSPU1rIqL6S7N-bSBfgbU=", "test_dataset": null, "holdout_dataset": null, "cross_experiment_params": {"cv_type": "NUycreDUBb5FHHTw49keVQh-W7yQ2b_hA6L0V9FvaTQ=", "runs": 1, "global_random_seed": 32, "random_seeds": null, "random_seed_bounds": [0, 100000]}, "to_csv_params": {}}, "train_features": null, "platform": "gaofandeMacBook-Air.local", "source_script": "/Users/gaofan/Desktop/FeatureEngineering/HyperparameterHunter.py", "notes": "", "aggregates": {"times": {"runs": [[[0.206495], [0.167029], [0.180479], [0.177945], [0.18318], [0.171827], [0.170457], [0.161556], [0.189537], [0.179828]]], "folds": [[0.230561, 0.183072, 0.195177, 0.193698, 0.199411, 0.188215, 0.184153, 0.176931, 0.205456, 0.194733]], "reps": [2.038776], "total_elapsed": 2.049299, "start": "2019-10-08 16:16:07.051823", "end": "2019-10-08 16:16:09.101124"}, "evaluations": {"oof_roc_auc_score": {"runs": [[[0.9545454545454545], [0.9356060606060607], [0.9047619047619048], [0.9623015873015873], [0.9246031746031746], [0.9146825396825398], [0.9861111111111112], [0.9333333333333332], [0.9761904761904762], [0.9714285714285714]]], "folds": [[0.9545454545454545, 0.9356060606060607, 0.9047619047619048, 0.9623015873015873, 0.9246031746031746, 0.9146825396825398, 0.9861111111111112, 0.9333333333333332, 0.9761904761904762, 0.9714285714285714]], "reps": [0.9464153585962687], "final": 0.9464153585962687}}}}